[{"Pressed": "Key.shift"}, {"Held": "Key.shift"}, {"Held": "'H'"}, {"Released": "'H'"}, {"Released": "Key.shift"}, {"Pressed": "'i'"}, {"Held": "'i'"}, {"Released": "'i'"}, {"Pressed": "Key.shift_r"}, {"Held": "Key.shift_r"}, {"Held": "'!'"}, {"Released": "Key.shift_r"}, {"Released": "'1'"}, {"Pressed": "Key.space"}, {"Held": "Key.space"}, {"Released": "Key.space"}, {"Pressed": "Key.shift_r"}, {"Held": "Key.shift_r"}, {"Held": "'E'"}, {"Released": "Key.shift_r"}, {"Released": "'e'"}, {"Pressed": "'v'"}, {"Held": "'v'"}, {"Released": "'v'"}, {"Pressed": "'e'"}, {"Held": "'e'"}, {"Held": "'r'"}, {"Released": "'e'"}, {"Pressed": "'y'"}, {"Held": "'y'"}, {"Released": "'r'"}, {"Released": "'y'"}, {"Pressed": "'o'"}, {"Held": "'o'"}, {"Held": "'n'"}, {"Released": "'o'"}, {"Released": "'n'"}, {"Pressed": "'e'"}, {"Held": "'e'"}, {"Released": "'e'"}, {"Pressed": "'t'"}, {"Held": "'t'"}, {"Held": "'h'"}, {"Released": "'t'"}, {"Pressed": "'i'"}, {"Held": "'i'"}, {"Released": "'h'"}, {"Pressed": "'s'"}, {"Held": "'s'"}, {"Released": "'i'"}, {"Released": "'s'"}, {"Pressed": "Key.space"}, {"Held": "Key.space"}, {"Held": "'i'"}, {"Released": "Key.space"}, {"Released": "'i'"}, {"Pressed": "'s'"}, {"Held": "'s'"}, {"Released": "'s'"}, {"Pressed": "'b'"}, {"Held": "'b'"}, {"Released": "'b'"}, {"Pressed": "'a'"}, {"Held": "'a'"}, {"Released": "'a'"}, {"Pressed": "'s'"}, {"Held": "'s'"}, {"Released": "'s'"}, {"Pressed": "'i'"}, {"Held": "'i'"}, {"Released": "'i'"}, {"Pressed": "'c'"}, {"Held": "'c'"}, {"Released": "'c'"}, {"Pressed": "Key.space"}, {"Held": "Key.space"}, {"Released": "Key.space"}, {"Pressed": "'k'"}, {"Held": "'k'"}, {"Released": "'k'"}, {"Pressed": "'e'"}, {"Held": "'e'"}, {"Released": "'e'"}, {"Pressed": "'y'"}, {"Held": "'y'"}, {"Released": "'y'"}, {"Pressed": "'l'"}, {"Held": "'l'"}, {"Released": "'l'"}, {"Pressed": "'o'"}, {"Held": "'o'"}, {"Released": "'o'"}, {"Pressed": "'g'"}, {"Held": "'g'"}, {"Released": "'g'"}, {"Pressed": "'g'"}, {"Held": "'g'"}, {"Released": "'g'"}, {"Pressed": "'e'"}, {"Held": "'e'"}, {"Held": "'r'"}, {"Released": "'e'"}, {"Released": "'r'"}, {"Pressed": "Key.space"}, {"Held": "Key.space"}, {"Released": "Key.space"}, {"Pressed": "'p'"}, {"Held": "'p'"}, {"Released": "'p'"}, {"Pressed": "'o'"}, {"Held": "'o'"}, {"Released": "'o'"}, {"Pressed": "'g'"}, {"Held": "'g'"}, {"Released": "'g'"}, {"Pressed": "'r'"}, {"Held": "'r'"}, {"Held": "'a'"}, {"Released": "'r'"}, {"Released": "'a'"}, {"Pressed": "Key.backspace"}, {"Held": "Key.backspace"}, {"Released": "Key.backspace"}, {"Pressed": "Key.backspace"}, {"Held": "Key.backspace"}, {"Released": "Key.backspace"}, {"Pressed": "Key.backspace"}, {"Held": "Key.backspace"}, {"Released": "Key.backspace"}, {"Pressed": "Key.backspace"}, {"Held": "Key.backspace"}, {"Released": "Key.backspace"}, {"Pressed": "'r'"}, {"Held": "'r'"}, {"Held": "'o'"}, {"Released": "'r'"}, {"Released": "'o'"}, {"Pressed": "'g'"}, {"Held": "'g'"}, {"Released": "'g'"}, {"Pressed": "'r'"}, {"Held": "'r'"}, {"Held": "'a'"}, {"Released": "'r'"}, {"Pressed": "'m'"}, {"Held": "'m'"}, {"Released": "'a'"}, {"Released": "'m'"}, {"Pressed": "Key.shift"}, {"Held": "Key.shift"}, {"Held": "'H'"}, {"Released": "'H'"}, {"Released": "Key.shift"}, {"Pressed": "'i'"}, {"Held": "'i'"}, {"Released": "'i'"}, {"Pressed": "Key.shift_r"}, {"Held": "Key.shift_r"}, {"Held": "'!'"}, {"Released": "Key.shift_r"}, {"Released": "'1'"}, {"Pressed": "Key.shift_r"}, {"Held": "Key.shift_r"}, {"Held": "'E'"}, {"Released": "Key.shift_r"}, {"Released": "'e'"}, {"Pressed": "'v'"}, {"Held": "'v'"}, {"Released": "'v'"}, {"Pressed": "'e'"}, {"Held": "'e'"}, {"Held": "'r'"}, {"Released": "'e'"}, {"Released": "'r'"}, {"Pressed": "'y'"}, {"Held": "'y'"}, {"Released": "'y'"}, {"Pressed": "'o'"}, {"Held": "'o'"}, {"Held": "'n'"}, {"Released": "'o'"}, {"Released": "'n'"}, {"Pressed": "'e'"}, {"Held": "'e'"}, {"Released": "'e'"}, {"Pressed": "'t'"}, {"Held": "'t'"}, {"Released": "'t'"}, {"Pressed": "'h'"}, {"Held": "'h'"}, {"Released": "'h'"}, {"Pressed": "'i'"}, {"Held": "'i'"}, {"Released": "'i'"}, {"Pressed": "'s'"}, {"Held": "'s'"}, {"Released": "'s'"}, {"Pressed": "'i'"}, {"Held": "'i'"}, {"Held": "'s'"}, {"Released": "'i'"}, {"Released": "'s'"}, {"Pressed": "'a'"}, {"Held": "'a'"}, {"Released": "'a'"}, {"Pressed": "'s'"}, {"Held": "'s'"}, {"Held": "'i'"}, {"Released": "'s'"}, {"Released": "'i'"}, {"Pressed": "'m'"}, {"Held": "'m'"}, {"Released": "'m'"}, {"Pressed": "'p'"}, {"Held": "'p'"}, {"Released": "'p'"}, {"Pressed": "'l'"}, {"Held": "'l'"}, {"Released": "'l'"}, {"Pressed": "'e'"}, {"Held": "'e'"}, {"Released": "'e'"}, {"Pressed": "'k'"}, {"Held": "'k'"}, {"Released": "'k'"}, {"Pressed": "'e'"}, {"Held": "'e'"}, {"Held": "'y'"}, {"Released": "'e'"}, {"Released": "'y'"}, {"Pressed": "'l'"}, {"Held": "'l'"}, {"Released": "'l'"}, {"Pressed": "'o'"}, {"Held": "'o'"}, {"Released": "'o'"}, {"Pressed": "'g'"}, {"Held": "'g'"}, {"Released": "'g'"}, {"Pressed": "'g'"}, {"Held": "'g'"}, {"Released": "'g'"}, {"Pressed": "'e'"}, {"Held": "'e'"}, {"Held": "'r'"}, {"Released": "'e'"}, {"Released": "'r'"}, {"Pressed": "'p'"}, {"Held": "'p'"}, {"Released": "'p'"}, {"Pressed": "'r'"}, {"Held": "'r'"}, {"Held": "'o'"}, {"Released": "'r'"}, {"Released": "'o'"}, {"Pressed": "'g'"}, {"Held": "'g'"}, {"Released": "'g'"}, {"Pressed": "'r'"}, {"Held": "'r'"}, {"Held": "'a'"}, {"Released": "'r'"}, {"Pressed": "'m'"}, {"Held": "'m'"}, {"Released": "'a'"}, {"Released": "'m'"}, {"Pressed": "'f'"}, {"Held": "'f'"}, {"Released": "'f'"}, {"Pressed": "'o'"}, {"Held": "'o'"}, {"Released": "'o'"}, {"Pressed": "'r'"}, {"Held": "'r'"}, {"Released": "'r'"}, {"Pressed": "'o'"}, {"Held": "'o'"}, {"Held": "'u'"}, {"Released": "'o'"}, {"Pressed": "'r'"}, {"Held": "'r'"}, {"Released": "'u'"}, {"Released": "'r'"}, {"Pressed": "'p'"}, {"Held": "'p'"}, {"Released": "'p'"}, {"Pressed": "'r'"}, {"Held": "'r'"}, {"Held": "'o'"}, {"Released": "'r'"}, {"Released": "'o'"}, {"Pressed": "'j'"}, {"Held": "'j'"}, {"Released": "'j'"}, {"Pressed": "'e'"}, {"Held": "'e'"}, {"Released": "'e'"}, {"Pressed": "'c'"}, {"Held": "'c'"}, {"Released": "'c'"}, {"Pressed": "'t'"}, {"Held": "'t'"}, {"Released": "'t'"}, {"Pressed": "'.'"}, {"Held": "'.'"}, {"Released": "'.'"}, {"Pressed": "Key.shift_r"}, {"Held": "Key.shift_r"}, {"Held": "'T'"}, {"Released": "Key.shift_r"}, {"Released": "'t'"}, {"Pressed": "'h'"}, {"Held": "'h'"}, {"Released": "'h'"}, {"Pressed": "'a'"}, {"Held": "'a'"}, {"Released": "'a'"}, {"Pressed": "'n'"}, {"Held": "'n'"}, {"Released": "'n'"}, {"Pressed": "'k'"}, {"Held": "'k'"}, {"Released": "'k'"}, {"Pressed": "Key.shift"}, {"Held": "Key.shift"}, {"Held": "'Y'"}, {"Released": "'Y'"}, {"Released": "Key.shift"}, {"Pressed": "'o'"}, {"Held": "'o'"}, {"Held": "'u'"}, {"Released": "'o'"}, {"Released": "'u'"}, {"Pressed": "Key.shift_r"}, {"Held": "Key.shift_r"}, {"Held": "'A'"}, {"Released": "Key.shift_r"}, {"Released": "'a'"}, {"Pressed": "'l'"}, {"Held": "'l'"}, {"Released": "'l'"}, {"Pressed": "'l'"}, {"Held": "'l'"}, {"Released": "'l'"}, {"Pressed": "Key.shift_r"}, {"Held": "Key.shift_r"}, {"Held": "'!'"}, {"Released": "Key.shift_r"}, {"Released": "'1'"}]